odoo/addons/product_packaging_calculator/README.rst
odoo/addons/product_packaging_calculator/__init__.py
odoo/addons/product_packaging_calculator/__manifest__.py
odoo/addons/product_packaging_calculator/hooks.py
odoo/addons/product_packaging_calculator/i18n/it.po
odoo/addons/product_packaging_calculator/i18n/product_packaging_calculator.pot
odoo/addons/product_packaging_calculator/i18n/stock_packaging_calculator.pot
odoo/addons/product_packaging_calculator/models/__init__.py
odoo/addons/product_packaging_calculator/models/product.py
odoo/addons/product_packaging_calculator/models/product_qty_by_packaging_mixin.py
odoo/addons/product_packaging_calculator/readme/CONTRIBUTORS.md
odoo/addons/product_packaging_calculator/readme/CREDITS.md
odoo/addons/product_packaging_calculator/readme/DESCRIPTION.md
odoo/addons/product_packaging_calculator/readme/ROADMAP.md
odoo/addons/product_packaging_calculator/readme/USAGE.md
odoo/addons/product_packaging_calculator/static/description/icon.png
odoo/addons/product_packaging_calculator/static/description/index.html
odoo/addons/product_packaging_calculator/tests/__init__.py
odoo/addons/product_packaging_calculator/tests/common.py
odoo/addons/product_packaging_calculator/tests/models.py
odoo/addons/product_packaging_calculator/tests/test_packaging_calc.py
odoo/addons/product_packaging_calculator/tests/test_pkg_qty_str.py
odoo/addons/product_packaging_calculator/tests/test_product_qty_by_packaging_mixin.py
odoo/addons/product_packaging_calculator/tests/utils.py
odoo_addon_product_packaging_calculator-18.0.1.0.0.2.dist-info/METADATA
odoo_addon_product_packaging_calculator-18.0.1.0.0.2.dist-info/WHEEL
odoo_addon_product_packaging_calculator-18.0.1.0.0.2.dist-info/top_level.txt
odoo_addon_product_packaging_calculator-18.0.1.0.0.2.dist-info/RECORD
